SafeSeal/Encryption.py
SafeSeal/__init__.py
SafeSeal-1.1.0.dist-info/METADATA
SafeSeal-1.1.0.dist-info/WHEEL
SafeSeal-1.1.0.dist-info/top_level.txt
SafeSeal-1.1.0.dist-info/RECORD
