Metadata-Version: 2.2
Name: SafeSeal
Version: 1.1.0
Summary: A multi-layered encryption and decryption library in Python.
Home-page: https://github.com/altikrity1/SafeSeal
Author: Abdullah Mustafa
Author-email: abdaullahtkh@gmail.com
Classifier: Programming Language :: Python :: 3
Classifier: License :: OSI Approved :: MIT License
Classifier: Operating System :: OS Independent
Requires-Python: >=3.6
Dynamic: author
Dynamic: author-email
Dynamic: classifier
Dynamic: description
Dynamic: description-content-type
Dynamic: home-page
Dynamic: requires-python
Dynamic: summary
